asyncore_wsgi/SimpleWebSocketServer.py
asyncore_wsgi/__init__.py
asyncore_wsgi-0.0.9.dist-info/METADATA
asyncore_wsgi-0.0.9.dist-info/RECORD
asyncore_wsgi-0.0.9.dist-info/WHEEL
asyncore_wsgi-0.0.9.dist-info/top_level.txt
