Metadata-Version: 2.1
Name: asyncore-wsgi
Version: 0.0.9
Summary: Asynchronous WSGI and WebSocket server based on asyncore module
Home-page: https://github.com/romanvm/asyncore-wsgi
Author: Roman Miroshnychenko
Author-email: roman1972@gmail.com
License: MIT
Platform: UNKNOWN
Classifier: Development Status :: 4 - Beta
Classifier: Environment :: Web Environment
Classifier: Intended Audience :: Developers
Classifier: License :: OSI Approved :: MIT License
Classifier: Programming Language :: Python
Classifier: Programming Language :: Python :: 2
Classifier: Programming Language :: Python :: 2.7
Classifier: Programming Language :: Python :: 3
Classifier: Operating System :: OS Independent
Classifier: Topic :: Internet :: WWW/HTTP
Classifier: Topic :: Internet :: WWW/HTTP :: WSGI :: Server
